goodman_pipeline/__init__.py
goodman_pipeline/version.py
goodman_pipeline/core/__init__.py
goodman_pipeline/core/check_version.py
goodman_pipeline/core/core.py
goodman_pipeline/core/tests/__init__.py
goodman_pipeline/core/tests/test_ccdproc.py
goodman_pipeline/core/tests/test_check_version.py
goodman_pipeline/core/tests/test_core.py
goodman_pipeline/data/dcr_source/README.md
goodman_pipeline/data/dcr_source/dcr/dcr.c
goodman_pipeline/data/dcr_source/dcr/dcr.h
goodman_pipeline/data/dcr_source/dcr/dcr.par
goodman_pipeline/data/dcr_source/dcr/makefile
goodman_pipeline/data/dcr_source/dcr/pfitshead.c
goodman_pipeline/data/dcr_source/dcr/pfitshead.h
goodman_pipeline/data/dcr_source/dcr/pfitsin.c
goodman_pipeline/data/dcr_source/dcr/pfitsin.h
goodman_pipeline/data/dcr_source/dcr/pfitsio.c
goodman_pipeline/data/dcr_source/dcr/pfitsio.h
goodman_pipeline/data/dcr_source/dcr/swap.c
goodman_pipeline/data/dcr_source/dcr/swap.h
goodman_pipeline/data/nist_list/nist_air_strong_lines_Ar.txt
goodman_pipeline/data/nist_list/nist_air_strong_lines_Cu.txt
goodman_pipeline/data/nist_list/nist_air_strong_lines_Fe.txt
goodman_pipeline/data/nist_list/nist_air_strong_lines_He.txt
goodman_pipeline/data/nist_list/nist_air_strong_lines_Hg.txt
goodman_pipeline/data/nist_list/nist_air_strong_lines_Ne.txt
goodman_pipeline/data/params/config.json
goodman_pipeline/data/params/config_example.json
goodman_pipeline/data/params/dcr.par
goodman_pipeline/data/params/param.json
goodman_pipeline/data/ref_comp/goodman_comp_1200M1_Ar.fits
goodman_pipeline/data/ref_comp/goodman_comp_1200M1_CuHeAr.fits
goodman_pipeline/data/ref_comp/goodman_comp_1200M1_FeHeAr.fits
goodman_pipeline/data/ref_comp/goodman_comp_1200M2_CuHeAr.fits
goodman_pipeline/data/ref_comp/goodman_comp_1200M2_FeHeAr.fits
goodman_pipeline/data/ref_comp/goodman_comp_1200M3_CuHeAr.fits
goodman_pipeline/data/ref_comp/goodman_comp_1200M3_FeHeAr.fits
goodman_pipeline/data/ref_comp/goodman_comp_1200M4_GG455_CuHeAr.fits
goodman_pipeline-1.3.13.dist-info/licenses/LICENSE
goodman_pipeline-1.3.13.dist-info/METADATA
goodman_pipeline-1.3.13.dist-info/WHEEL
goodman_pipeline-1.3.13.dist-info/entry_points.txt
goodman_pipeline-1.3.13.dist-info/top_level.txt
goodman_pipeline-1.3.13.dist-info/RECORD
