Metadata-Version: 2.4
Name: goodman_pipeline
Version: 1.3.13
Summary: Pipeline for reducing Goodman HTS data.
Author-email: Simón Torres <simon.torres@noirlab.edu>, Bruno Quint <bruno.quint@noirlab.edu>, César Briceño <cesar.briceno@noirlab.edu>, David Sanmartim <dsanmartim@lsst.org>
Maintainer-email: Simón Torres <simon.torres@noirlab.edu>
License: BSD 3-Clause License
Project-URL: Homepage, https://soardocs.readthedocs.io/projects/goodman-pipeline/en/latest/
Project-URL: Bug Reports, https://github.com/soar-telescope/goodman_pipeline/issues
Project-URL: Source, https://github.com/soar-telescope/goodman_pipeline
Keywords: soar,pipelines,astronomy,images,spectroscopy
Classifier: Development Status :: 5 - Production/Stable
Classifier: Environment :: Console
Classifier: Intended Audience :: Developers
Classifier: Intended Audience :: Education
Classifier: Intended Audience :: Science/Research
Classifier: License :: OSI Approved :: BSD License
Classifier: Programming Language :: Python :: 3.8
Classifier: Programming Language :: Python :: 3.9
Classifier: Programming Language :: Python :: 3.10
Classifier: Programming Language :: Python :: 3.11
Classifier: Programming Language :: Python :: 3.12
Classifier: Natural Language :: English
Classifier: Operating System :: POSIX :: Linux
Classifier: Operating System :: POSIX :: Other
Classifier: Operating System :: MacOS :: MacOS X
Classifier: Topic :: Scientific/Engineering :: Astronomy
Classifier: Topic :: Scientific/Engineering :: Information Analysis
Classifier: Topic :: Software Development :: Libraries :: Python Modules
Requires-Python: >=3.8
License-File: LICENSE
Requires-Dist: astropy
Requires-Dist: astroplan
Requires-Dist: ccdproc
Requires-Dist: cython
Requires-Dist: matplotlib
Requires-Dist: numpy
Requires-Dist: packaging
Requires-Dist: pandas
Requires-Dist: requests
Requires-Dist: scipy
Provides-Extra: test
Requires-Dist: mock; extra == "test"
Dynamic: license-file
